importpatch.py
importpatch-0.1.3.dist-info/METADATA
importpatch-0.1.3.dist-info/WHEEL
importpatch-0.1.3.dist-info/top_level.txt
importpatch-0.1.3.dist-info/RECORD
